{
  "Name": "金罡珠",
  "Description": [
    "大罗金仙修炼千年的内丹。",
    "防御+90"
  ],
  "Bitmap": 13,
  "Price": 10000,
  "Scope": {
    "Usable": false,
    "Throwable": false,
    "Equipable": true,
    "Sellable": true,
    "Consuming": false,
    "ApplyToAllHero": false,
    "ApplyToAllEnemy": false,
    "EquipableByHero_0": true,
    "EquipableByHero_1": true,
    "EquipableByHero_2": true,
    "EquipableByHero_3": true,
    "EquipableByHero_4": true,
    "EquipableByHero_5": true
  },
  "Script": {
    "Use": "Null",
    "Equip": "Item_00201_Equip",
    "Throw": "Null"
  }
}