{
  "Comment": "盛装月如",
  "Frame": {
    "VanishTime": 0,
    "StillTime": 0,
    "LayerOffset": 0,
    "SpriteID": 245,
    "SpriteFrames": 3,
    "Pos": {
      "Pos": {
        "X": 704,
        "Y": 752
      },
      "Direction": 0,
      "FrameID": 0
    }
  },
  "Status": {
    "Display": false,
    "IsObstacle": false,
    "IsAutoTrigger": true,
    "TriggerDistance": 2
  },
  "Script": {
    "SrcTrigger": "Event_00035_00015_Trigger",
    "ScrAuto": "Null"
  },
  "ScriptFrame": {
    "TriggerIdleFrame": 0,
    "AutoIdleFrame": 0
  }
}