{
  "Name": "疾风靴",
  "Description": [
    "以薄如云雾的蝉纱织成，",
    "助穿者疾行如风。",
    "防御+14 身法+17"
  ],
  "Bitmap": 100,
  "Price": 5700,
  "Scope": {
    "Usable": false,
    "Throwable": false,
    "Equipable": true,
    "Sellable": true,
    "Consuming": true,
    "ApplyToAllHero": false,
    "ApplyToAllEnemy": false,
    "EquipableByHero_0": true,
    "EquipableByHero_1": true,
    "EquipableByHero_2": true,
    "EquipableByHero_3": true,
    "EquipableByHero_4": true,
    "EquipableByHero_5": true
  },
  "Script": {
    "Use": "Null",
    "Equip": "Item_00182_Equip",
    "Throw": "Null"
  }
}