{
  "Name": "一阳指",
  "Description": [
    "聚劲食指，发出刚猛的气芒，",
    "攻击敌方单人。"
  ],
  "BaseDamage": 130,
  "CostMP": 18,
  "SoundID": 130,
  "SummonID": -1,
  "Genus": {
    "Sword": true,
    "Wind": false,
    "Thunder": false,
    "Water": false,
    "Fire": false,
    "Earth": false,
    "Poison": false,
    "Sorcery": false,
    "Ultimate": false,
    "Angel": false,
    "Evil": false,
    "Heal": false,
    "Buff": false
  },
  "AttackMode": 0,
  "Frame": {
    "BitmapID": 8,
    "OffsetPos": {
      "X": 48,
      "Y": 32
    },
    "LayerOffset": 0,
    "Preview": 0,
    "Speed": 0,
    "KeepEffect": true,
    "TotalTimes": 0,
    "Shake": 0,
    "Wave": 0
  },
  "Scope": {
    "UsableOutsideBattle": false,
    "UsableInBattle": true,
    "UsableToHero": true,
    "UsableToEnemy": false,
    "ApplyToAllHero": false,
    "ApplyToAllEnemy": false
  },
  "Script": {
    "Success": "Null",
    "Use": "Null"
  }
}